OCI_Inference/OCI_Inference.py
OCI_Inference/__init__.py
OCI_Inference-0.1.0.dist-info/METADATA
OCI_Inference-0.1.0.dist-info/WHEEL
OCI_Inference-0.1.0.dist-info/top_level.txt
OCI_Inference-0.1.0.dist-info/RECORD
