Metadata-Version: 2.1
Name: OCI_Inference
Version: 0.1.0
Summary: A packages for sending the inference request to OCI GenAI models
Home-page: 
Author: Sakthivel Thangaraj
Author-email: sakthiveltvt.thangaraj@gmail.com
Classifier: Programming Language :: Python :: 3.12
Classifier: Topic :: Software Development :: Libraries :: Python Modules
Classifier: License :: OSI Approved :: MIT License
Classifier: Operating System :: OS Independent
Requires-Python: >=3.9
Requires-Dist: oci
